{
  "id": "81",
  "name": "التكوير",
  "remark": "",
  "ayaTranslation": [
    {
      "id": "1",
      "text": "Apabila matahari digulung,"
    },
    {
      "id": "2",
      "text": "dan apabila bintang-bintang berjatuhan,"
    },
    {
      "id": "3",
      "text": "dan apabila gunung-gunung dihancurkan,"
    },
    {
      "id": "4",
      "text": "dan apabila unta-unta yang bunting ditinggalkan (tidak diperdulikan)"
    },
    {
      "id": "5",
      "text": "dan apabila binatang-binatang liar dikumpulkan,"
    },
    {
      "id": "6",
      "text": "dan apabila lautan dijadikan meluap"
    },
    {
      "id": "7",
      "text": "dan apabila ruh-ruh dipertemukan (dengan tubuh)"
    },
    {
      "id": "8",
      "text": "dan apabila bayi-bayi perempuan yang dikubur hidup-hidup ditanya,"
    },
    {
      "id": "9",
      "text": "karena dosa apakah dia dibunuh,"
    },
    {
      "id": "10",
      "text": "dan apabila catatan-catatan (amal perbuatan manusia) dibuka,"
    },
    {
      "id": "11",
      "text": "dan apabila langit dilenyapkan,"
    },
    {
      "id": "12",
      "text": "dan apabila neraka Jahim dinyalakan,"
    },
    {
      "id": "13",
      "text": "dan apabila surga didekatkan,"
    },
    {
      "id": "14",
      "text": "maka tiap-tiap jiwa akan mengetahui apa yang telah dikerjakannya."
    },
    {
      "id": "15",
      "text": "Sungguh, Aku bersumpah dengan bintang-bintang,"
    },
    {
      "id": "16",
      "text": "yang beredar dan terbenam,"
    },
    {
      "id": "17",
      "text": "demi malam apabila telah hampir meninggalkan gelapnya,"
    },
    {
      "id": "18",
      "text": "dan demi subuh apabila fajarnya mulai menyingsing,"
    },
    {
      "id": "19",
      "text": "sesungguhnya Al Quran itu benar-benar firman (Allah yang dibawa oleh) utusan yang mulia (Jibril),"
    },
    {
      "id": "20",
      "text": "yang mempunyai kekuatan, yang mempunyai kedudukan tinggi di sisi Allah yang mempunyai 'Arsy,"
    },
    {
      "id": "21",
      "text": "yang ditaati di sana (di alam malaikat) lagi dipercaya."
    },
    {
      "id": "22",
      "text": "Dan temanmu (Muhammad) itu bukanlah sekali-kali orang yang gila."
    },
    {
      "id": "23",
      "text": "Dan sesungguhnya Muhammad itu melihat Jibril di ufuk yang terang."
    },
    {
      "id": "24",
      "text": "Dan dia (Muhammad) bukanlah orang yang bakhil untuk menerangkan yang ghaib."
    },
    {
      "id": "25",
      "text": "Dan Al Quran itu bukanlah perkataan syaitan yang terkutuk,"
    },
    {
      "id": "26",
      "text": "maka ke manakah kamu akan pergi?"
    },
    {
      "id": "27",
      "text": "Al Quran itu tiada lain hanyalah peringatan bagi semesta alam,"
    },
    {
      "id": "28",
      "text": "(yaitu) bagi siapa di antara kamu yang mau menempuh jalan yang lurus."
    },
    {
      "id": "29",
      "text": "Dan kamu tidak dapat menghendaki (menempuh jalan itu) kecuali apabila dikehendaki Allah, Tuhan semesta alam."
    }
  ]
}